{
  "entries": [
    {
      "b": 63,
      "g": 64,
      "label": "red",
      "r": 77
    },
    {
      "b": 63,
      "g": 64,
      "label": "blue",
      "r": 77
    },
    {
      "b": 145,
      "g": 83,
      "label": "red",
      "r": 165
    },
    {
      "b": 237,
      "g": 179,
      "label": "green",
      "r": 67
    },
    {
      "b": 69,
      "g": 63,
      "label": "red",
      "r": 24
    },
    {
      "b": 76,
      "g": 203,
      "label": "green",
      "r": 77
    },
    {
      "b": 54,
      "g": 177,
      "label": "blue",
      "r": 45
    },
    {
      "b": 232,
      "g": 249,
      "label": "submit",
      "r": 189
    },
    {
      "b": 41,
      "g": 105,
      "label": "submit",
      "r": 150
    },
    {
      "b": 107,
      "g": 63,
      "label": "submit",
      "r": 28
    },
    {
      "b": 161,
      "g": 53,
      "label": "submit",
      "r": 159
    },
    {
      "b": 131,
      "g": 184,
      "label": "blue",
      "r": 205
    },
    {
      "b": 225,
      "g": 190,
      "label": "blue",
      "r": 211
    },
    {
      "b": 187,
      "g": 93,
      "label": "red",
      "r": 149
    },
    {
      "b": 73,
      "g": 202,
      "label": "green",
      "r": 152
    },
    {
      "b": 139,
      "g": 249,
      "label": "blue",
      "r": 42
    },
    {
      "b": 176,
      "g": 181,
      "label": "green",
      "r": 46
    },
    {
      "b": 160,
      "g": 124,
      "label": "blue",
      "r": 113
    },
    {
      "b": 76,
      "g": 97,
      "label": "red",
      "r": 202
    },
    {
      "b": 76,
      "g": 97,
      "label": "green",
      "r": 202
    },
    {
      "b": 76,
      "g": 97,
      "label": "blue",
      "r": 202
    },
    {
      "b": 76,
      "g": 97,
      "label": "submit",
      "r": 202
    },
    {
      "b": 76,
      "g": 97,
      "label": "submit",
      "r": 202
    },
    {
      "b": 76,
      "g": 97,
      "label": "blue",
      "r": 202
    },
    {
      "b": 76,
      "g": 97,
      "label": "green",
      "r": 202
    },
    {
      "b": 76,
      "g": 97,
      "label": "red",
      "r": 202
    },
    {
      "b": 21,
      "g": 203,
      "label": "green",
      "r": 243
    },
    {
      "b": 151,
      "g": 251,
      "label": "red",
      "r": 62
    },
    {
      "b": 202,
      "g": 136,
      "label": "red",
      "r": 93
    },
    {
      "b": 28,
      "g": 164,
      "label": "green",
      "r": 65
    },
    {
      "b": 9,
      "g": 184,
      "label": "green",
      "r": 153
    },
    {
      "b": 207,
      "g": 52,
      "label": "red",
      "r": 2
    },
    {
      "b": 186,
      "g": 252,
      "label": "green",
      "r": 146
    },
    {
      "b": 211,
      "g": 32,
      "label": "blue",
      "r": 55
    },
    {
      "b": 192,
      "g": 126,
      "label": "submit",
      "r": 75
    },
    {
      "b": 120,
      "g": 168,
      "label": "red",
      "r": 200
    }
  ]
}
